setup.py
priyagaussbinom/Binomialdistribution.py
priyagaussbinom/Gaussiandistribution.py
priyagaussbinom/Generaldistribution.py
priyagaussbinom/__init__.py
priyagaussbinom.egg-info/PKG-INFO
priyagaussbinom.egg-info/SOURCES.txt
priyagaussbinom.egg-info/dependency_links.txt
priyagaussbinom.egg-info/not-zip-safe
priyagaussbinom.egg-info/top_level.txt